nas_sync_script_builder/__init__.py
nas_sync_script_builder/__main__.py
nas_sync_script_builder/cli.py
nas_sync_script_builder/config.py
nas_sync_script_builder/constants.py
nas_sync_script_builder/gui.py
nas_sync_script_builder/partitions.py
nas_sync_script_builder/template.py
nas_sync_script_builder/templates/nas-sync.sh.tpl
nas_sync_script_builder-0.4.0.dist-info/licenses/LICENSE
nas_sync_script_builder-0.4.0.dist-info/METADATA
nas_sync_script_builder-0.4.0.dist-info/WHEEL
nas_sync_script_builder-0.4.0.dist-info/entry_points.txt
nas_sync_script_builder-0.4.0.dist-info/top_level.txt
nas_sync_script_builder-0.4.0.dist-info/RECORD
