Metadata-Version: 2.4
Name: nas-sync-script-builder
Version: 0.4.0
Summary: GUI tool to generate a bash script for one-way, no-deletion NAS sync using rsync and lsyncd
Author: Jinjinov
Maintainer: Jinjinov
License: MIT License
Project-URL: Repository, https://github.com/Jinjinov/nas-sync-script-builder
Project-URL: Issues, https://github.com/Jinjinov/nas-sync-script-builder/issues
Project-URL: Releases, https://github.com/Jinjinov/nas-sync-script-builder/releases
Keywords: nas,rsync,lsyncd,gui,backup
Classifier: Programming Language :: Python :: 3
Classifier: Operating System :: POSIX :: Linux
Classifier: Topic :: System :: Archiving :: Backup
Requires-Python: >=3.10
License-File: LICENSE
Requires-Dist: PySide6
Requires-Dist: Jinja2
Requires-Dist: PyYAML
Requires-Dist: pydbus
Requires-Dist: PyGObject
Dynamic: license-file
